Spruce_settings-0.2.2-py2.7-nspkg.pth
spruce/settings/_exc.py
spruce/settings/_conf.py
spruce/settings/_inmemory.py
spruce/settings/_core.py
spruce/settings/__init__.py
Spruce_settings-0.2.2.dist-info/top_level.txt
Spruce_settings-0.2.2.dist-info/RECORD
Spruce_settings-0.2.2.dist-info/pydist.json
Spruce_settings-0.2.2.dist-info/WHEEL
Spruce_settings-0.2.2.dist-info/namespace_packages.txt
Spruce_settings-0.2.2.dist-info/METADATA
Spruce_settings-0.2.2.dist-info/entry_points.txt
Spruce_settings-0.2.2.dist-info/DESCRIPTION.rst
