Metadata-Version: 2.0
Name: Spruce-settings
Version: 0.2.2
Summary: Application settings
Home-page: UNKNOWN
Author: Ivan D Vasin
Author-email: nisavid@gmail.com
License: GNU LESSER GENERAL PUBLIC LICENSE
Requires-Dist: spruce-collections
